[
  {
    "url": "https://www.youtube.com/watch?v=XqZsoesa55w",
    "songName": "song1"
  },
  {
    "url": "https://www.youtube.com/watch?v=e_04ZrNroTo",
    "songName": "song2"
  },
  {
    "url": "https://www.youtube.com/watch?v=IhJVli-hQo4",
    "songName": "song3"
  },
  {
    "url": "https://www.youtube.com/watch?v=JJzZNPy1yZU",
    "songName": "song4"
  },
  {
    "url": "https://www.youtube.com/watch?v=HA9ISkl9bzA",
    "songName": "song5"
  },
  {
    "url": "https://www.youtube.com/watch?v=qSsMW5p6DW8",
    "songName": "song6"
  },
  {
    "url": "https://www.youtube.com/watch?v=u7GkPe1JLOw",
    "songName": "song7"
  },
  {
    "url": "https://www.youtube.com/watch?v=rGwnzzj62rs",
    "songName": "song8"
  },
  {
    "url": "https://www.youtube.com/watch?v=uQU2TWDhASM",
    "songName": "song9"
  },
  {
    "url": "https://www.youtube.com/watch?v=k85mRPqvMbE",
    "songName": "song10"
  }
]